[
  {
    "id": "325c20b1-c907-4ae9-8119-283fc5340b10",
    "title": "Where Does Money Come From? 💵",
    "description": "Explore how money is made and where it comes from!",
    "category": "earning",
    "ageGroup": "big",
    "videoType": "youtube",
    "videoUrl": "https://www.youtube.com/watch?v=XNu5ppFZbHo",
    "videoId": "XNu5ppFZbHo",
    "thumbnailUrl": null,
    "duration": 420,
    "difficulty": "medium",
    "isPublished": true,
    "sortOrder": 6,
    "createdAt": "2025-10-23T08:39:31.238Z",
    "updatedAt": "2025-10-23T08:39:31.238Z"
  },
  {
    "id": "10714362-971e-4a0b-a571-c8caa682d4bc",
    "title": "The Money Song 🪙",
    "description": "Learn about pennies, nickels, dimes, and quarters with a catchy song!",
    "category": "earning",
    "ageGroup": "big",
    "videoType": "youtube",
    "videoUrl": "https://www.youtube.com/watch?v=pnXJGNo08v0",
    "videoId": "pnXJGNo08v0",
    "thumbnailUrl": null,
    "duration": 240,
    "difficulty": "easy",
    "isPublished": true,
    "sortOrder": 2,
    "createdAt": "2025-10-23T08:39:31.238Z",
    "updatedAt": "2025-10-23T08:39:31.238Z"
  },
  {
    "id": "4d3e17d1-6169-4520-8e56-ba0cddc75766",
    "title": "USA Coins & Bills Song 💵",
    "description": "Fun song teaching about American money - coins and dollar bills!",
    "category": "saving",
    "ageGroup": "little",
    "videoType": "youtube",
    "videoUrl": "https://www.youtube.com/watch?v=7QW5Qw81yIY",
    "videoId": "7QW5Qw81yIY",
    "thumbnailUrl": null,
    "duration": 180,
    "difficulty": "easy",
    "isPublished": true,
    "sortOrder": 1,
    "createdAt": "2025-10-23T08:39:31.238Z",
    "updatedAt": "2025-10-23T08:39:31.238Z"
  },
  {
    "id": "c6d02eaa-9d58-49ed-b9af-bd461da44ba8",
    "title": "Wants vs Needs 🎯",
    "description": "Learn the difference between wants and needs to make smart choices!",
    "category": "budgeting",
    "ageGroup": "big",
    "videoType": "youtube",
    "videoUrl": "https://www.youtube.com/watch?v=kzwkXdylS7E",
    "videoId": "kzwkXy lS7E",
    "thumbnailUrl": null,
    "duration": 300,
    "difficulty": "easy",
    "isPublished": true,
    "sortOrder": 3,
    "createdAt": "2025-10-23T08:39:31.238Z",
    "updatedAt": "2025-10-23T08:39:31.238Z"
  },
  {
    "id": "3e5957db-b565-469c-a8a4-7de8a3018295",
    "title": "How to Make a Budget 📊",
    "description": "Simple budgeting basics for kids - learn to plan your money!",
    "category": "budgeting",
    "ageGroup": "teen",
    "videoType": "youtube",
    "videoUrl": "https://www.youtube.com/watch?v=1eG5g6h8shg",
    "videoId": "1eG5g6h8shg",
    "thumbnailUrl": null,
    "duration": 360,
    "difficulty": "medium",
    "isPublished": true,
    "sortOrder": 4,
    "createdAt": "2025-10-23T08:39:31.238Z",
    "updatedAt": "2025-10-23T08:39:31.238Z"
  },
  {
    "id": "418f640a-0f18-4553-8d38-bc20c601c2da",
    "title": "Saving Money Goals 🎯",
    "description": "Learn how to save money and reach your savings goals!",
    "category": "saving",
    "ageGroup": "big",
    "videoType": "youtube",
    "videoUrl": "https://www.youtube.com/watch?v=RQ3RdVSlkb0",
    "videoId": "RQ3RdVSlkb0",
    "thumbnailUrl": null,
    "duration": 270,
    "difficulty": "easy",
    "isPublished": true,
    "sortOrder": 5,
    "createdAt": "2025-10-23T08:39:31.238Z",
    "updatedAt": "2025-10-23T08:39:31.238Z"
  },
  {
    "id": "50d5ff5f-4450-4f68-bd17-f501982255c2",
    "title": "Smart Shopping for Kids 🛍️",
    "description": "Learn how to be a smart shopper and make good money choices!",
    "category": "spending",
    "ageGroup": "teen",
    "videoType": "youtube",
    "videoUrl": "https://www.youtube.com/watch?v=g4-cGkD3ads",
    "videoId": "g4-cGkD3ads",
    "thumbnailUrl": null,
    "duration": 330,
    "difficulty": "medium",
    "isPublished": true,
    "sortOrder": 7,
    "createdAt": "2025-10-23T08:39:31.238Z",
    "updatedAt": "2025-10-23T08:39:31.238Z"
  },
  {
    "id": "55f56bbe-5703-4075-82ad-920f723b70c5",
    "title": "Sharing and Giving 💝",
    "description": "Learn about the joy of sharing and helping others with money!",
    "category": "giving",
    "ageGroup": "big",
    "videoType": "youtube",
    "videoUrl": "https://www.youtube.com/watch?v=5Wv0cAtLyxA",
    "videoId": "5Wv0cAtLyxA",
    "thumbnailUrl": null,
    "duration": 210,
    "difficulty": "easy",
    "isPublished": true,
    "sortOrder": 8,
    "createdAt": "2025-10-23T08:39:31.238Z",
    "updatedAt": "2025-10-23T08:39:31.238Z"
  },
  {
    "id": "2251d714-3d7e-457a-827b-58211e4d95b6",
    "title": "Earning an Allowance 💰",
    "description": "Learn about earning allowance and managing your own money!",
    "category": "earning",
    "ageGroup": "teen",
    "videoType": "youtube",
    "videoUrl": "https://www.youtube.com/watch?v=Yn_gw8OhLts",
    "videoId": "Yn_gw8OhLts",
    "thumbnailUrl": null,
    "duration": 390,
    "difficulty": "medium",
    "isPublished": true,
    "sortOrder": 9,
    "createdAt": "2025-10-23T08:39:31.238Z",
    "updatedAt": "2025-10-23T08:39:31.238Z"
  },
  {
    "id": "d6707a1b-3313-477d-90d1-270ff13e86b4",
    "title": "Making Change 🏪",
    "description": "Learn how to count money and make change when shopping!",
    "category": "spending",
    "ageGroup": "big",
    "videoType": "youtube",
    "videoUrl": "https://www.youtube.com/watch?v=dFzAU3u06Ps",
    "videoId": "dFzAU3u06Ps",
    "thumbnailUrl": null,
    "duration": 300,
    "difficulty": "medium",
    "isPublished": true,
    "sortOrder": 10,
    "createdAt": "2025-10-23T08:39:31.238Z",
    "updatedAt": "2025-10-23T08:39:31.238Z"
  }
]